{"type":"FeatureCollection","features":[{"type":"Feature","id":1,"geometry":{"type":"Point","coordinates":[101.98123261435157,4.9749934439371852]},"properties":{"OBJECTID":1,"Name":"Podunk","Entry1_page":"12","Entry1_date":"64-12-01","Entry1":"Lorem ipsum dolor sit amet, consectetur adipiscing elit, sed do eiusmod tempor incididunt ut labore et dolore magna aliqua. Ut enim ad minim veniam, quis nostrud exercitation ullamco laboris nisi ut aliquip ex ea commodo consequat. Duis aute irure dolor in reprehenderit in voluptate velit esse cillum dolore eu fugiat nulla pariatur. Excepteur sint occaecat cupidatat non proident, sunt in culpa qui officia deserunt mollit anim id est laborum","Entry2_page":"22","Entry2_date":null,"Entry2":null,"Entry3_page":null,"Entry3_date":null,"Entry3":null,"Entry4_page":null,"Entry4_date":null,"Entry4":null,"Comments":null,"Visit":null,"Historical":null,"Report":null,"Placeconn":null,"Categories":null,"Start_date":null,"End_date":null,"Country":null,"State":null,"District":null,"Notebook":null}}]}